simple_speak/__init__.py
simple_speak/speak_command/__init__.py
simple_speak/speak_command/speak_command.py
simple_speak/waka_command/PocketSphinx.py
simple_speak/waka_command/__init__.py
simple_speak/waka_command/command_api.py
simple_speak/waka_command/pyaudio_demo.py
simple_speak/waka_command/waka_command.py
simple_speak/waka_command/command_tasks/WeatherAPITest.py
simple_speak/waka_command/command_tasks/__init__.py
simple_speak/waka_command/command_tasks/baidu_spider.py
simple_speak/waka_command/command_tasks/time_know.py
simple_speak/waka_command/command_tasks/tools/__init__.py
simple_speak/waka_command/command_tasks/tools/user_agent.py
simple_speak-0.0.1.dist-info/METADATA
simple_speak-0.0.1.dist-info/WHEEL
simple_speak-0.0.1.dist-info/top_level.txt
simple_speak-0.0.1.dist-info/RECORD
