Metadata-Version: 2.1
Name: simple-speak
Version: 0.0.1
Summary: 语音控制，增加了唤醒命令以及程序任务接口、部分接口程序
Home-page: https://github.com/reporter-law/speak_command
Author: cw
Author-email: 1063117365@qq.com
License: GPL Licence
Keywords: baidu-aip,speech_recognition,pyaudio
Platform: any
Requires-Python: >=3.7.*
Requires-Dist: pyaudio
Requires-Dist: requests
Requires-Dist: pydub
Requires-Dist: baidu-aip
Requires-Dist: numpy
Requires-Dist: jieba
Requires-Dist: fuzzywuzzy
Requires-Dist: SpeechRecognition
Requires-Dist: schedule
Requires-Dist: lxml
